gnucashxml/__init__.py
gnucashxml/gnucashxml.py
gnucashxml/setup.py
gnucashxml-1.1.dist-info/METADATA
gnucashxml-1.1.dist-info/WHEEL
gnucashxml-1.1.dist-info/top_level.txt
gnucashxml-1.1.dist-info/RECORD
