Metadata-Version: 2.1
Name: gnucashxml
Version: 1.1
Summary: Open GnuCash XML book
Home-page: UNKNOWN
Author: David A Nagy
Author-email: dalexnagy@gmail.com>
License: UNKNOWN
Keywords: python,gnucashxml
Platform: UNKNOWN
Classifier: Development Status :: 5 - Production/Stable
Classifier: Intended Audience :: End Users/Desktop
Classifier: Programming Language :: Python :: 3
